ddg3.py
ddg3-0.6.8.dist-info/LICENSE
ddg3-0.6.8.dist-info/METADATA
ddg3-0.6.8.dist-info/WHEEL
ddg3-0.6.8.dist-info/entry_points.txt
ddg3-0.6.8.dist-info/top_level.txt
ddg3-0.6.8.dist-info/RECORD
