Metadata-Version: 2.1
Name: ddg3
Version: 0.6.8
Summary: Library for querying the Duck Duck Go API, updated for python3
Home-page: https://github.com/jpetrucciani/python-duckduckgo
Author: Michael Stephens, Jacobi Petrucciani
Author-email: jacobi@mimirhq.com
License: BSD
Platform: any
Classifier: Development Status :: 4 - Beta
Classifier: Intended Audience :: Developers
Classifier: License :: OSI Approved :: BSD License
Classifier: Operating System :: OS Independent
Classifier: Programming Language :: Python
Classifier: Topic :: Internet :: WWW/HTTP :: Indexing/Search
Classifier: Programming Language :: Python :: 3
Classifier: Programming Language :: Python :: 3.6
Classifier: Programming Language :: Python :: 3.7
Classifier: Programming Language :: Python :: 3.8
Classifier: Programming Language :: Python :: 3.9
Requires-Dist: requests
